useragent_api/__init__.py
useragent_api-3.1.5.dist-info/METADATA
useragent_api-3.1.5.dist-info/WHEEL
useragent_api-3.1.5.dist-info/RECORD
