Metadata-Version: 2.1
Name: useragent-api
Version: 3.1.5
Summary: A package used to retrieve a database of up-to-date browser useragents.
Author: useragents-me
Requires-Python: >=3.10,<4.0
Classifier: Programming Language :: Python :: 3
Classifier: Programming Language :: Python :: 3.10
Classifier: Programming Language :: Python :: 3.11
Classifier: Programming Language :: Python :: 3.12
